setup.py
waaazzi/__init__.py
waaazzi/friends.py
waaazzi/setup.cfg.py
waaazzi.egg-info/PKG-INFO
waaazzi.egg-info/SOURCES.txt
waaazzi.egg-info/dependency_links.txt
waaazzi.egg-info/not-zip-safe
waaazzi.egg-info/top_level.txt