Metadata-Version: 1.0
Name: waaazzi
Version: 0.1
Summary: friends
Home-page: UNKNOWN
Author: Wasif Ibrahim
Author-email: wasif.ibrahim29@gmail.com
License: UNKNOWN
Platform: UNKNOWN
